Metadata-Version: 1.1
Name: tfimageutils
Version: 0.1.3
Summary: A utility package for dealing with image inputs into Tensorflow
Home-page: https://github.com/MrTrustworthy/tfimageutils
Author: MrTrustworthy
Author-email: tinywritingmakesmailhardtoread@gmail.com
License: MIT
Download-URL: https://github.com/MrTrustworthy/tfimageutils/archive/0.1.3.tar.gz
Keywords: tensorflow,image,utils
Platform: UNKNOWN
